paranoid/__init__.py
paranoid/flask.py
paranoid/models.py
paranoid/tests.py
sqla_paranoid3-0.1.4.dist-info/METADATA
sqla_paranoid3-0.1.4.dist-info/WHEEL
sqla_paranoid3-0.1.4.dist-info/top_level.txt
sqla_paranoid3-0.1.4.dist-info/RECORD
