Metadata-Version: 2.1
Name: sqla-paranoid3
Version: 0.1.4
Summary: Brings transparent soft delete to SQLAlchemy ORM
Author: Sasha Hilton
Author-email: sashahilton00@gmail.com
License: MIT
Requires-Dist: sqlalchemy
Requires-Dist: Flask-SQLAlchemy
